raimad/__init__.py
raimad/__main__.py
raimad/affine.py
raimad/annotation.py
raimad/ansec.py
raimad/bbox.py
raimad/boundbbox.py
raimad/boundpoint.py
raimad/circle.py
raimad/cli.py
raimad/compo.py
raimad/custompoly.py
raimad/dictlist.py
raimad/empty.py
raimad/err.py
raimad/fortune.py
raimad/graphviz.py
raimad/helpers.py
raimad/iters.py
raimad/jupyter.py
raimad/layer.py
raimad/mark.py
raimad/option.py
raimad/partial.py
raimad/proxy.py
raimad/rectlw.py
raimad/rectwire.py
raimad/show.py
raimad/snowman.py
raimad/string_import.py
raimad/svg.py
raimad/transform.py
raimad/typing.py
raimad/cif/__init__.py
raimad/cif/noreuse.py
raimad/cif/shorthand.py
raimad-1.2.4.dist-info/licenses/LICENSE.md
raimad-1.2.4.dist-info/METADATA
raimad-1.2.4.dist-info/WHEEL
raimad-1.2.4.dist-info/entry_points.txt
raimad-1.2.4.dist-info/top_level.txt
raimad-1.2.4.dist-info/RECORD
