Metadata-Version: 2.4
Name: raimad
Version: 1.2.4
Summary: RAIMAD Astronomical Instrument MAsk Designer
Author-email: maybetree <maybetree48@proton.me>
License-Expression: GPL-3.0-only
Classifier: Programming Language :: Python :: 3
Requires-Python: >=3.10
License-File: LICENSE.md
Requires-Dist: typing-extensions
Dynamic: license-file
